cpc_abi/__init__.py
cpc_abi/abi.py
cpc_abi/base.py
cpc_abi/constants.py
cpc_abi/decoding.py
cpc_abi/encoding.py
cpc_abi/exceptions.py
cpc_abi/grammar.py
cpc_abi/py.typed
cpc_abi/registry.py
cpc_abi/utils/__init__.py
cpc_abi/utils/numeric.py
cpc_abi/utils/padding.py
cpc_abi/utils/parsing.py
cpc_abi-1.3.4.dist-info/LICENSE
cpc_abi-1.3.4.dist-info/METADATA
cpc_abi-1.3.4.dist-info/WHEEL
cpc_abi-1.3.4.dist-info/top_level.txt
cpc_abi-1.3.4.dist-info/RECORD
