Metadata-Version: 2.1
Name: cpc-abi
Version: 1.3.4
Summary: CPChain ABI Utils
Home-page: https://github.com/cpchain/cpc-abi
Author: Piper Merriam
Author-email: pipermerriam@gmail.com
License: MIT
Keywords: ethereum
Platform: UNKNOWN
Classifier: Development Status :: 5 - Production/Stable
Classifier: Intended Audience :: Developers
Classifier: License :: OSI Approved :: BSD License
Classifier: Natural Language :: English
Classifier: Programming Language :: Python :: 3
Classifier: Programming Language :: Python :: 3.5
Classifier: Programming Language :: Python :: 3.6
Classifier: Programming Language :: Python :: Implementation :: PyPy
Requires-Dist: eth-utils (<2.0.0,>=1.2.0)
Requires-Dist: eth-typing (<3.0.0,>=2.0.0)
Requires-Dist: parsimonious (<0.9.0,>=0.8.0)
Provides-Extra: doc
Requires-Dist: Sphinx (<2,>=1.6.5) ; extra == 'doc'
Requires-Dist: sphinx-rtd-theme (>=0.1.9) ; extra == 'doc'
